array_api_negative_index/__init__.py
array_api_negative_index/_main.py
array_api_negative_index/py.typed
array_api_negative_index-1.0.0.dist-info/licenses/LICENSE
array_api_negative_index-1.0.0.dist-info/METADATA
array_api_negative_index-1.0.0.dist-info/WHEEL
array_api_negative_index-1.0.0.dist-info/top_level.txt
array_api_negative_index-1.0.0.dist-info/RECORD
