Metadata-Version: 2.4
Name: array-api-negative-index
Version: 1.0.0
Summary: Utils for indexing arrays with {-n, -(n-1), ..., -1, 0, 1, ..., n-1, n} using array API.
Author-email: 34j <34j.95a2p@simplelogin.com>
License: MIT
Project-URL: Bug Tracker, https://github.com/34j/array-api-negative-index/issues
Project-URL: Changelog, https://github.com/34j/array-api-negative-index/blob/main/CHANGELOG.md
Project-URL: documentation, https://array-api-negative-index.readthedocs.io
Project-URL: repository, https://github.com/34j/array-api-negative-index
Classifier: Development Status :: 2 - Pre-Alpha
Classifier: Intended Audience :: Developers
Classifier: Natural Language :: English
Classifier: Operating System :: OS Independent
Classifier: Programming Language :: Python :: 3.9
Classifier: Programming Language :: Python :: 3.10
Classifier: Programming Language :: Python :: 3.11
Classifier: Programming Language :: Python :: 3.12
Classifier: Programming Language :: Python :: 3.13
Classifier: Topic :: Software Development :: Libraries
Requires-Python: >=3.9
License-File: LICENSE
Requires-Dist: array-api-compat>=1.11.2
Requires-Dist: types-array-api>=1.1.4
Dynamic: license-file
